github_repo_analyzer/__init__.py
github_repo_analyzer/analyzer.py
github_repo_analyzer/cli.py
github_repo_analyzer/utils.py
github_repo_analyzer-0.1.1.dist-info/METADATA
github_repo_analyzer-0.1.1.dist-info/WHEEL
github_repo_analyzer-0.1.1.dist-info/entry_points.txt
github_repo_analyzer-0.1.1.dist-info/licenses/LICENSE
github_repo_analyzer-0.1.1.dist-info/RECORD
