Metadata-Version: 2.4
Name: github-repo-analyzer
Version: 0.1.1
Summary: Convert GitHub repositories to markdown with detailed analysis
Project-URL: Homepage, https://github.com/dsamuelhodge/github-repo-analyzer
Project-URL: Bug Tracker, https://github.com/dsamuelhodge/github-repo-analyzer/issues
Author-email: Derrick Hodge <copilot@hodgedomain.com>
License-File: LICENSE
Classifier: License :: OSI Approved :: MIT License
Classifier: Operating System :: OS Independent
Classifier: Programming Language :: Python :: 3
Requires-Python: >=3.7
Requires-Dist: gitpython>=3.1.0
Requires-Dist: rich>=10.0.0
Requires-Dist: tiktoken>=0.3.0
